gshellx/__init__.py
gshellx/config.py
gshellx/history.json
gshellx/main.py
gshellx/openai_api.py
gshellx/output.txt
gshellx/prompts.py
gshellx/shell_utils.py
gshellx-0.1.0.dist-info/METADATA
gshellx-0.1.0.dist-info/WHEEL
gshellx-0.1.0.dist-info/entry_points.txt
gshellx-0.1.0.dist-info/RECORD
