Metadata-Version: 2.1
Name: gshellx
Version: 0.1.0
Summary: Python CLI app for generating shell commands with OpenAI's GPT-3.5-turbo model
License: MIT
Author: Tomer 
Author-email: chaim.tomer@gmail.com
Requires-Python: >=3.7.0,<4.0
Classifier: License :: OSI Approved :: MIT License
Classifier: Programming Language :: Python :: 3
Classifier: Programming Language :: Python :: 3.7
Classifier: Programming Language :: Python :: 3.8
Classifier: Programming Language :: Python :: 3.9
Classifier: Programming Language :: Python :: 3.10
Classifier: Programming Language :: Python :: 3.11
Requires-Dist: click (>=8.1.3,<9.0.0)
Requires-Dist: prompt-toolkit (>=3.0.38,<4.0.0)
Requires-Dist: pytest (>=7.3.1,<8.0.0)
Requires-Dist: requests (>=2.31.0,<3.0.0)
Requires-Dist: rich (>=13.3.5,<14.0.0)
